mytypo.py
mytypo-0.1.0.dist-info/LICENSE.txt
mytypo-0.1.0.dist-info/METADATA
mytypo-0.1.0.dist-info/WHEEL
mytypo-0.1.0.dist-info/entry_points.txt
mytypo-0.1.0.dist-info/top_level.txt
mytypo-0.1.0.dist-info/RECORD
